lambda_response_utils/__init__.py
lambda_response_utils/encoders.py
lambda_response_utils/exceptions.py
lambda_response_utils/helpers.py
lambda_response_utils/response.py
lambda_response_utils/status.py
lambdakit_response-1.0.2.dist-info/METADATA
lambdakit_response-1.0.2.dist-info/WHEEL
lambdakit_response-1.0.2.dist-info/top_level.txt
lambdakit_response-1.0.2.dist-info/RECORD
