Metadata-Version: 2.4
Name: lambdakit-response
Version: 1.0.2
Summary: Lightweight response utility for AWS Lambda proxy integration
Author: mtrshuvo
Author-email: mtrshuvo@gmail.com
Classifier: Programming Language :: Python :: 3
Classifier: Operating System :: OS Independent
Requires-Python: >=3.7
Requires-Dist: orjson>=3.9.0
Dynamic: author
Dynamic: author-email
Dynamic: classifier
Dynamic: requires-dist
Dynamic: requires-python
Dynamic: summary
